referral/__init__.py
referral/admin.py
referral/apps.py
referral/models.py
referral/serializers.py
referral/tests.py
referral/urls.py
referral/views.py
referral/migrations/0001_initial.py
referral/migrations/__init__.py
django_referral2-0.1.0.dist-info/METADATA
django_referral2-0.1.0.dist-info/WHEEL
django_referral2-0.1.0.dist-info/top_level.txt
django_referral2-0.1.0.dist-info/RECORD
