Metadata-Version: 2.1
Name: django-referral2
Version: 0.1.0
Summary: A reusable Django referral system app
Home-page: https://github.com/Andrew-oduola/django-referral
Author: Andrew Oduola
Author-email: andrewoduola@gmail.com
License: MIT
Classifier: Framework :: Django
Classifier: Programming Language :: Python
Classifier: Programming Language :: Python :: 3
Requires-Dist: Django>=4.2
